edx_argoutils/__init__.py
edx_argoutils/bigquery.py
edx_argoutils/common.py
edx_argoutils/edx_api_client.py
edx_argoutils/email_unsubscribes.py
edx_argoutils/hubspot_leads.py
edx_argoutils/mysql.py
edx_argoutils/paypal.py
edx_argoutils/paypal_xml.py
edx_argoutils/record.py
edx_argoutils/s3.py
edx_argoutils/sitemap.py
edx_argoutils/snowflake.py
edx_argoutils/vault_secrets.py
edx_argoutils-1.0.14.dist-info/AUTHORS.rst
edx_argoutils-1.0.14.dist-info/LICENSE.txt
edx_argoutils-1.0.14.dist-info/METADATA
edx_argoutils-1.0.14.dist-info/WHEEL
edx_argoutils-1.0.14.dist-info/entry_points.txt
edx_argoutils-1.0.14.dist-info/top_level.txt
edx_argoutils-1.0.14.dist-info/RECORD
