Metadata-Version: 2.1
Name: edx-argoutils
Version: 1.0.14
Summary: Utility code to assist in writing Argo Flows.
Home-page: https://github.com/2uinc/edx-argoutils
Author: Abdul Rafey
Author-email: arafey@2u.com
License: AGPL
Keywords: edx_argoutils
Classifier: Development Status :: 2 - Pre-Alpha
Classifier: Intended Audience :: Developers
Classifier: Natural Language :: English
Classifier: License :: OSI Approved :: GNU Affero General Public License v3
Classifier: Programming Language :: Python :: 3
Classifier: Programming Language :: Python :: 3.8
Requires-Python: >=3.8
License-File: LICENSE.txt
License-File: AUTHORS.rst
Requires-Dist: prefect[aws,google,snowflake,viz]==1.4.1
Requires-Dist: importlib-metadata==8.4.0
Requires-Dist: botocore
Requires-Dist: boto3
Requires-Dist: ciso8601
Requires-Dist: mysql-connector-python==8.0.21
Requires-Dist: edx-opaque-keys
Requires-Dist: backoff
Requires-Dist: paramiko
Requires-Dist: hvac
